har2pm/__init__.py
har2pm/cli.py
har2pm/common.py
har2pm/har2postman.py
har2pm-0.1.9.dist-info/entry_points.txt
har2pm-0.1.9.dist-info/LICENSE
har2pm-0.1.9.dist-info/METADATA
har2pm-0.1.9.dist-info/WHEEL
har2pm-0.1.9.dist-info/RECORD
