Metadata-Version: 2.1
Name: har2pm
Version: 0.1.9
Summary: Convert HAR(HTTP Archive) to Postman Collection
Home-page: https://github.com/whitexie/Har2Postman
License: MIT
Keywords: har,postman
Author: ysansan
Requires-Python: >=3.6,<4.0
Classifier: License :: OSI Approved :: MIT License
Classifier: Programming Language :: Python :: 3
Classifier: Programming Language :: Python :: 3.6
Classifier: Programming Language :: Python :: 3.7
Classifier: Programming Language :: Python :: 3.8
Classifier: Programming Language :: Python :: 3.9
Classifier: Programming Language :: Python :: 3.10
Classifier: Programming Language :: Python :: 3.11
Requires-Dist: jmespath (>=0.10.0,<0.11.0)
Project-URL: Repository, https://github.com/whitexie/Har2Postman
